ram/ram.sv
module ram #(
    parameter WIDTH = 32, 
              DATA_W = 8
) (
    input  logic  clk_i,
    input  logic  write_en_i,
    input  logic  AddrsCtrl_i,
    input  logic [WIDTH-1:0] a_i,
    input  logic [WIDTH-1:0] wd_i,
    output logic [WIDTH-1:0] rd_o
);

logic [DATA_W-1:0] ram_array [32'h1FFF : 32'h1000]; 

initial begin 
    $display  ("Loading ram.");
    $readmemh ("data.mem", rom_array);
end;

always_ff @(posedge clk) begin
    if (write_en_i==1 & AddrsCtrl_i==1) begin
        ram_array[a_i] <= wd_i[31:24];
        ram_array[a_i + 1] <= wd_i[23:16];
        ram_array[a_i + 2] <= wd_i[15:8];
        ram_array[a_i + 3] <= wd_i[7:0];
    end

    if (write_en_i==1 & AddrsCtrl_i==0) 
        ram_array[a_i] <= wd_i[7:0];     
end 


always_comb  begin
    if (write_en_i==0 & AddrsCtrl_i==1)
    rd_o <=  {ram_array[a_i],rom_array[a_i+1],rom_array[a_i+2],rom_array[a_i+3]};
    
    if (write_en_i==0 & AddrsCtrl_i==0) begin
        //sign extension
        if (ram_array[a_i][7]==0) rd_o <= {{24'h0},{ram_array[a_i]}};
        if (ram_array[a_i][7]==1) rd_o <= {{24'hFFFFFF},{ram_array[a_i]}};
    end

end 

endmodule

ram/ram.vcd
$version Generated by VerilatedVcd $end
$date Tue Dec  6 12:28:28 2022 $end
$timescale 1ps $end

 $scope module TOP $end
  $var wire  1 % AddrsCtrl_i $end
  $var wire 32 & a_i [31:0] $end
  $var wire  1 # clk_i $end
  $var wire 32 ( rd_o [31:0] $end
  $var wire 32 ' wd_i [31:0] $end
  $var wire  1 $ write_en_i $end
  $scope module ram $end
   $var wire  1 % AddrsCtrl_i $end
   $var wire 32 * DATA_W [31:0] $end
   $var wire 32 ) WIDTH [31:0] $end
   $var wire 32 & a_i [31:0] $end
   $var wire  1 # clk_i $end
   $var wire 32 ( rd_o [31:0] $end
   $var wire 32 ' wd_i [31:0] $end
   $var wire  1 $ write_en_i $end
  $upscope $end
 $upscope $end
$enddefinitions $end


#0
0#
0$
1%
b00000000000000000000000000000000 &
b10101010101110111100110011011101 '
b00000000000000000000000000000000 (
b00000000000000000000000000100000 )
b00000000000000000000000000001000 *
#1
1#
b11011101110011001011101110101010 (
#2
0#
#3
1#
#4
0#
0%
b00000000000000000000000000000100 &
#5
1#
b00000000000000000000000000010001 (
#6
0#
1$
1%
b00000000000000000000000000001100 &
#7
1#
#8
0#
0%
#9
1#
#10
0#
0$
#11
1#
b11111111111111111111111111011101 (
