CPU/ram.sv
module ram #(
    parameter WIDTH = 32, 
              DATA_W = 8
) (
    input  logic  clk_i,
    input  logic  write_en_i,
    input  logic  AddrsCtrl_i,
    input  logic [WIDTH-1:0] a_i,
    input  logic [WIDTH-1:0] wd_i,

    
    output logic [WIDTH-1:0] rd_o
);

logic [DATA_W-1:0] ram_array [32'hFFF : 32'h0]; 

initial begin 
    $display  ("Loading ram.");
    $readmemh ("data.mem", ram_array);
end;

always_ff @(posedge clk_i) begin
    if (write_en_i==1 & AddrsCtrl_i==1) begin
        ram_array[a_i] <= wd_i[31:24];
        ram_array[a_i + 1] <= wd_i[23:16];
        ram_array[a_i + 2] <= wd_i[15:8];
        ram_array[a_i + 3] <= wd_i[7:0];
        $display(ram_array[a_i],ram_array[a_i + 1],ram_array[a_i + 2],ram_array[a_i + 3]);
        
    end

    if (write_en_i==1 & AddrsCtrl_i==0) begin
        ram_array[a_i] <= wd_i[7:0]; 
        $display (ram_array[a_i]);
    end    
end 


always_comb  begin
    if (write_en_i==0 & AddrsCtrl_i==1)
    rd_o =  {ram_array[a_i],ram_array[a_i+1],ram_array[a_i+2],ram_array[a_i+3]};
    
    
    if (write_en_i==0 & AddrsCtrl_i==0) begin
        //sign extension
        if (ram_array[a_i+3][7]==0) rd_o = {{24'h0},{ram_array[a_i + 3]}};
        if (ram_array[a_i+3][7]==1) rd_o = {{24'hFFFFFF},{ram_array[a_i + 3]}};
    end

end 

endmodule

ALU.sv
module ALU #(
    parameter DATAWIDTH =   32, 
            SHIFT_WIDTH = 5
)(
    input logic [DATAWIDTH-1:0]         SrcA_i,
    input logic [DATAWIDTH-1:0]         SrcB_i,
    input logic [3:0]                   ALUctrl_i,
    input logic [2:0]                   BranchCtrl_i,

    output logic [DATAWIDTH-1:0]        ALUResult_o,
    output logic                        Branch_o
);

logic signed [DATAWIDTH-1:0] SrcA_Signed;
logic signed [DATAWIDTH-1:0] SrcB_Signed;

assign SrcA_Signed = SrcA_i;
assign SrcB_Signed = SrcB_i;

always_comb begin
    case (BranchCtrl_i)
        //Equal
        3'b000: begin
                if(SrcA_i == SrcB_i) Branch_o = 1;
                else Branch_o = 0;
        end

        //Not equal
        3'b001: begin
                if(SrcA_i != SrcB_i) Branch_o = 1;
                else Branch_o = 0;
        end

        //<
        3'b010: begin
                    if(SrcA_Signed < SrcB_Signed) Branch_o = 1;
                    else Branch_o = 0;
                end

        //>=
        3'b011: begin
                    if(SrcA_Signed >= SrcB_Signed) Branch_o = 1;
                    else Branch_o = 0;
                end

        //< unsigned
        3'b100: begin
                if(SrcA_i < SrcB_i) Branch_o = 1;
                else Branch_o = 0;
        end

        //>= unsigned
        3'b101: begin
                if(SrcA_i >= SrcB_i) Branch_o = 1;
                else Branch_o = 0;
        end

        default: Branch_o = 0;
    endcase
end

always_comb begin
    case (ALUctrl_i)
        //add
        4'b0000: ALUResult_o = SrcA_i + SrcB_i;

        //sub
        4'b0001: ALUResult_o = SrcA_i - SrcB_i;

        //bitwise and
        4'b0010: ALUResult_o = SrcA_i & SrcB_i;

        //bitwise or
        4'b0011: ALUResult_o = SrcA_i | SrcB_i;

        //bitwise xor
        4'b0100: ALUResult_o = SrcA_i ^ SrcB_i;

        //signed less than
        4'b0101: begin
                    if(SrcA_Signed >= SrcB_Signed) ALUResult_o = 0;
                    else ALUResult_o = 1;
                end
        //unsigned less than
        4'b0110: begin
                    if (SrcA_i >= SrcB_i) ALUResult_o = 0;
                    else ALUResult_o = 1;
                end
        
        //SRL
        4'b0111: ALUResult_o = SrcA_i >> shift;

        //SLL
        4'b0100: ALUResult_o = SrcA_i << shift;

        //SRA
        4'b1001: ALUResult_o = SrcA_Signed >>> SrcB_i[SHIFT_WIDTH-1:0];

        //SLA
        4'b1010: ALUResult_o = SrcA_Signed <<< SrcB_i[SHIFT_WIDTH-1:0];;   

        //LW
        4'b1111: ALUResult_o = SrcB_i;

        default: ALUResult_o = 0;
    endcase
    
end

endmodule

CPU/extend.sv
module extend # (
    parameter DATAWIDTH = 32
)(
    input logic [2:0]               ImmSrc_i,
    input logic [DATAWIDTH-1:0]     Imm_i,

    output logic [DATAWIDTH-1:0]    ImmExt_o
);

always_comb begin
    case (ImmSrc_i)
        //instruction[31:20]
        0'b000: ImmExt_o = {{21{Imm_i[31]}}, Imm_i[30:20]};

        //instruction[31:25], instruction[11:7]
        0'b001: ImmExt_o = {{21{Imm_i[31]}}, Imm_i[30:25], Imm_i[11:7]};

        //instruction[31], instruction[7], instruction[30:25], instruction[4:1]
        0'b010: ImmExt_o = {{20{Imm_i[31]}}, Imm_i[7], Imm_i[30:25], Imm_i[11:8], 1'b0};

        //instruction[31:12]
        0'b011: ImmExt_o = {{13{Imm_i[31]}}, Imm_i[30:12]};
        
        //instruction[31], instruction[19:12], instruction[11]instruction [30:21]
        0'b100: ImmExt_o = {{12{Imm_i[31]}}, Imm_i[19:12], Imm_i[11], Imm_i[30:21], 1'b0};

        default: ImmExt_o = 32'b0;
    endcase
end

endmodule

CPU/register_file.sv
module register_file #(
    parameter ADDRESS_WIDTH = 5,
                DATA_WIDTH = 32
)(
    input logic                             clk,
    input logic [ADDRESS_WIDTH-1:0]         AD1_i,
    input logic [ADDRESS_WIDTH-1:0]         AD2_i,
    input logic [ADDRESS_WIDTH-1:0]         AD3_i,
    input logic                             WE3_i,
    input logic [DATA_WIDTH-1:0]            WD3_i,

    output logic [DATA_WIDTH-1:0]           RD1_o,
    output logic [DATA_WIDTH-1:0]           RD2_o,
    output logic [DATA_WIDTH-1:0]           a0_o  
);

logic [DATA_WIDTH-1:0] register_array [2**ADDRESS_WIDTH-1:0];
logic [DATA_WIDTH-1:0] a1;

initial begin
    for (int i = 0; i < $size(register_array); i++) begin
        register_array[i] = 32'b0;
    end
end
always_ff @(posedge clk) begin
    if (WE3_i) register_array[AD3_i] <= WD3_i;
end
always_comb begin 
    RD1_o = register_array[AD1_i];
    RD2_o = register_array[AD2_i];
    
end
assign  a0_o = register_array[10];



endmodule

CPU/control.sv
module control (
    input logic [6:0]                   op_i,           // input opcode, last 7 bits of instr
    input logic [2:0]                   funct3_i,
    input logic                         funct7bit_i,    // bit 30 of instruction
    output logic                        memWrite_en_o,   // memory write enable         
    output logic                        regWrite_en_o,  // Register write enable
    output logic [3:0]                  ALUctrl_o,      // determines alu op
    output logic                        ALUsrc_o,       // selects immOp or regOp
    output logic [2:0]                  ImmSrc_o,       // control signal for sign extension
    output logic                        BranchSrc_o,    // gives control of PCsrc to branchctrl module
    output logic                        addrSelect_o,   // toggles between word / byte addressing in RAM
    output logic                        ResultSrc_o     // toggles between using ALUresult and ReadData from RAM. 
);

    assign memWrite_en_o = (op_i ==  7'b0100011) ? 1'b1 : 1'b0;
    assign BranchSrc_o = (op_i == 7'b1100011) ? 1'b1 : 1'b0;
    assign ALUsrc_o = ((op_i == 7'b0010011) || (op_i == 7'b0000011)) ? 1'b1 : 1'b0; 
    assign regWrite_en_o = ((op_i == 7'b0110011) || (op_i == 7'b0010011) || (op_i == 7'b0000011)) ? 1'b1 : 1'b0;
    assign ResultSrc_o = (op_i == 7'b0000011) ? 1'b1 : 1'b0;
    
    always_comb begin

        if (op_i == 7'b0010011) ImmSrc_o = 3'b000; // hack, taking this outside the case statement allow grouping cases below

        case (op_i)
            7'b0110011, 7'b0010011: // R-type and I-type bitwise instructions
                case (funct3_i) // switch-casing funct3, as this determines the ops
                    3'b000:
                        if (funct7bit_i) begin // bit 5 of funct7
                            ALUctrl_o = 4'b0001; // sub
                        end else begin
                            ALUctrl_o = 4'b0000; // add
                        end    
                    3'b001: ALUctrl_o = 4'b1000; // sll | slli
                    3'b010: ALUctrl_o = 4'b0101; // slt | slti
                    3'b011: ALUctrl_o = 4'b0110; // sltu | sltiu
                    3'b100: ALUctrl_o = 4'b0100; // xor | xori
                    3'b101:
                        if (funct7bit_i) begin
                            ALUctrl_o = 4'b1001; // shift right arithmetic
                        end else begin
                            ALUctrl_o = 4'b0111; // shift right logical
                        end
                    3'b110: ALUctrl_o = 4'b0011; // or  
                    3'b111: ALUctrl_o = 4'b0010; // and
                    default: ;
                endcase

            7'b1100011: ImmSrc_o = 3'b010; // B-Type instructions

            7'b0000011: begin // I-type load instructions
                ALUctrl_o = 4'b1111;
                ImmSrc_o = 3'b000;
                case (funct3_i)
                    3'b000: // lb
                        addrSelect_o = 1'b0;
                    3'b010: // lw
                        addrSelect_o = 1'b1;
                    default: $display("Load Half, Load Half Unsigned and Load Byte Unsigned have not been implemented!!");
                endcase
            end

            7'b0100011: begin // S-type instructions
                ALUctrl_o = 4'b1111;
                ImmSrc_o = 3'b001;
                case (funct3_i)
                    3'b000: // sb
                        addrSelect_o = 1'b0;
                    3'b010: // sw
                        addrSelect_o = 1'b1;
                    default: $display("Store Half has not been implemented!! ");
                endcase
            end 
            
            // 7'b0010111: // Add Upper Immediate to PC
            // 7'b0110111: // Load Upper Immediate
            // 7'b1100111: // Jump and Link Register
            // 7'b1101111: // Jump and Link 

            default: ImmSrc_o = 3'b000; // this should have no effect if ALUsrc is 0, just precaution
        endcase
    end

endmodule

CPU/rom.sv
module rom #(
    parameter  WIDTH = 32, 
               DATA_W = 8, //because we have PC+4 so 4 * 8 = 32 bits
               PC_W = 12
)(
    input  logic [PC_W-1:0] a_i,
    output logic [WIDTH-1:0] rd_o
);

logic [DATA_W-1:0] rom_array [32'hBFC00FFF : 32'hBFC00000]; 

initial begin 
    $display ("Loading rom.");
    $readmemh("instructions.mem", rom_array);
end;

always_comb begin 
    rd_o = {rom_array[a_i-32'hBFC00000],rom_array[a_i+1-32'hBFC00000],rom_array[a_i+2-32'hBFC00000],rom_array[a_i+3-32'hBFC00000]}; // I do concatenation to get 32 bits( the instruction) from 8 bit parts
end

endmodule

CPU/PC.sv
module PC #(
    DW=32

) (
    input logic             clk,
    input logic             rst,
    input logic   [DW-1:0]  PC_i,
    output logic  [DW-1:0]  PC_o
);
    
    always_ff @(posedge clk ) begin
        if (rst) PC_o<=32'b0;
        else PC_o<=PC_i;
    end

endmodule

CPU/top.sv
module top #(
    parameter DW=32
) (
    input logic rst,
    input logic trigger_i,
    input logic clk,

    output logic [DW-1:0] data_out
);
   
    //pc wires
    logic [DW-1:0]        inc_PC;
    logic [DW-1:0]     branch_PC;
    logic [DW-1:0]       next_PC;
    logic [DW-1:0]       PC_wire;
    logic              PCsrcWire;
    //alu wires
    logic [DW-1:0]       RD1Wire;
    logic [DW-1:0]       RD2Wire;
    logic [DW-1:0]    Aluop2Wire;
    logic             branchWire;
    logic [DW-1:0] ALUResultWire;
    
    // rom wires
    logic [DW-1:0] InstructionWire;
    // control wires
    logic [6:0] opcode;
    logic [2:0] funct3;
    logic funct7;
    logic memWrite_enWire;
    logic regWrite_enWire;
    logic [3:0] ALUctrlWire;
    logic ALUsrcWire;
    logic [2:0] ImmSrcWire;
    logic BranchSrcWire;
    logic addrSelectWire;
    logic ResultSrcWire;
    // register wires
    logic [4:0] rs1Wire;
    logic [4:0] rs2Wire;
    logic [4:0] rdWire;
    logic [DW-1:0] wd3Wire;
    // extend wire
    logic [DW-1:0] ImmediateWire;
    logic [DW-1:0] ImmediateExtendWire;
    // ram wire
    logic [DW-1:0] RamOutWire;



    assign branch_PC=PC_wire+ImmediateExtendWire;
    assign inc_PC = PC_wire+4;
    assign next_PC = PCsrcWire ? branch_PC : inc_PC;
    
    PC PC(
        .clk(clk),
        .rst(rst),
        .PC_i(next_PC),

        .PC_o(PC_wire)
    );

    rom rom(
        .a_i(PC_wire),

        .rd_o(InstructionWire)
    );

    assign opcode = InstructionWire[6:0];
    assign funct3 = InstructionWire[14:12];
    assign funct7 = InstructionWire[30];

    control control(
        .op_i(opcode),
        .funct3_i(funct3),
        .funct7bit_i(funct7),

        .memWrite_en_o(memWrite_enWire),
        .regWrite_en_o(regWrite_enWire),
        .ALUctrl_o(ALUctrlWire),
        .ALUsrc_o(ALUsrcWire),
        .ImmSrc_o(ImmSrcWire),
        .BranchSrc_o(BranchSrcWire),
        .addrSelect_o(addrSelectWire),
        .ResultSrc_o(ResultSrcWire)
    );
    assign rs1Wire=InstructionWire[19:15];
    assign rs2Wire=InstructionWire[24:20];
    assign rdWire=InstructionWire[11:7];


    register_file register_file(
        .clk(clk),
        .AD1_i(rs1Wire),
        .AD2_i(rs2Wire),
        .AD3_i(rdWire),
        .WE3_i(regWrite_enWire),
        .WD3_i(wd3Wire),

        .RD1_o(RD1Wire),
        .RD2_o(RD2Wire),
        .a0_o(data_out)
    );

    assign ImmediateWire=InstructionWire;
    
    extend extend(
        .ImmSrc_i(ImmSrcWire),
        .Imm_i(ImmediateWire),

        .ImmExt_o(ImmediateExtendWire)
    );
    assign Aluop2Wire=ALUsrcWire ? ImmediateExtendWire : RD2Wire;

    ALU ALU(
        .SrcA_i(RD1Wire),
        .SrcB_i(Aluop2Wire),
        .ALUctrl_i(ALUctrlWire),
        .BranchCtrl_i(funct3),
        
        .ALUResult_o(ALUResultWire),
        .Branch_o(branchWire)
    );

    assign PCsrcWire = BranchSrcWire ? branchWire : 1'b0;

    ram ram(
        .clk_i(clk),
        .write_en_i(memWrite_enWire),
        .a_i(ALUResultWire),
        .AddrsCtrl_i(addrSelectWire),
        .wd_i(RD2Wire),

        .rd_o(RamOutWire)

    );

    assign wd3Wire = ResultSrcWire ? RamOutWire : ALUResultWire ;


endmodule

CPU/top.vcd
$version Generated by VerilatedVcd $end
$date Mon Dec  5 23:51:17 2022 $end
$timescale 1ps $end

 $scope module TOP $end
  $var wire  1 b clk $end
  $var wire 32 c data_out [31:0] $end
  $var wire  1 ` rst $end
  $var wire  1 a trigger_i $end
  $scope module top $end
   $var wire 32 - ALUResultWire [31:0] $end
   $var wire  4 4 ALUctrlWire [3:0] $end
   $var wire  1 5 ALUsrcWire $end
   $var wire 32 + Aluop2Wire [31:0] $end
   $var wire  1 7 BranchSrcWire $end
   $var wire 32 d DW [31:0] $end
   $var wire  3 6 ImmSrcWire [2:0] $end
   $var wire 32 > ImmediateExtendWire [31:0] $end
   $var wire 32 . ImmediateWire [31:0] $end
   $var wire 32 . InstructionWire [31:0] $end
   $var wire 32 ' PC_wire [31:0] $end
   $var wire  1 ( PCsrcWire $end
   $var wire 32 ) RD1Wire [31:0] $end
   $var wire 32 * RD2Wire [31:0] $end
   $var wire 32 ? RamOutWire [31:0] $end
   $var wire  1 9 ResultSrcWire $end
   $var wire  1 8 addrSelectWire $end
   $var wire  1 , branchWire $end
   $var wire 32 % branch_PC [31:0] $end
   $var wire  1 b clk $end
   $var wire 32 c data_out [31:0] $end
   $var wire  3 0 funct3 [2:0] $end
   $var wire  1 1 funct7 $end
   $var wire 32 $ inc_PC [31:0] $end
   $var wire  1 2 memWrite_enWire $end
   $var wire 32 & next_PC [31:0] $end
   $var wire  7 / opcode [6:0] $end
   $var wire  5 < rdWire [4:0] $end
   $var wire  1 3 regWrite_enWire $end
   $var wire  5 : rs1Wire [4:0] $end
   $var wire  5 ; rs2Wire [4:0] $end
   $var wire  1 ` rst $end
   $var wire  1 a trigger_i $end
   $var wire 32 = wd3Wire [31:0] $end
   $scope module ALU $end
    $var wire 32 - ALUResult_o [31:0] $end
    $var wire  4 4 ALUctrl_i [3:0] $end
    $var wire  3 0 BranchCtrl_i [2:0] $end
    $var wire  1 , Branch_o $end
    $var wire 32 d DATAWIDTH [31:0] $end
    $var wire 32 e SHIFT_WIDTH [31:0] $end
    $var wire 32 ) SrcA_Signed [31:0] $end
    $var wire 32 ) SrcA_i [31:0] $end
    $var wire 32 + SrcB_Signed [31:0] $end
    $var wire 32 + SrcB_i [31:0] $end
   $upscope $end
   $scope module PC $end
    $var wire 32 d DW [31:0] $end
    $var wire 32 & PC_i [31:0] $end
    $var wire 32 ' PC_o [31:0] $end
    $var wire  1 b clk $end
    $var wire  1 ` rst $end
   $upscope $end
   $scope module control $end
    $var wire  4 4 ALUctrl_o [3:0] $end
    $var wire  1 5 ALUsrc_o $end
    $var wire  1 7 BranchSrc_o $end
    $var wire  3 6 ImmSrc_o [2:0] $end
    $var wire  1 9 ResultSrc_o $end
    $var wire  1 8 addrSelect_o $end
    $var wire  3 0 funct3_i [2:0] $end
    $var wire  1 1 funct7bit_i $end
    $var wire  1 2 memWrite_en_o $end
    $var wire  7 / op_i [6:0] $end
    $var wire  1 3 regWrite_en_o $end
   $upscope $end
   $scope module extend $end
    $var wire 32 d DATAWIDTH [31:0] $end
    $var wire 32 > ImmExt_o [31:0] $end
    $var wire  3 6 ImmSrc_i [2:0] $end
    $var wire 32 . Imm_i [31:0] $end
   $upscope $end
   $scope module ram $end
    $var wire  1 8 AddrsCtrl_i $end
    $var wire 32 f DATA_W [31:0] $end
    $var wire 32 d WIDTH [31:0] $end
    $var wire 32 - a_i [31:0] $end
    $var wire  1 b clk_i $end
    $var wire 32 ? rd_o [31:0] $end
    $var wire 32 * wd_i [31:0] $end
    $var wire  1 2 write_en_i $end
   $upscope $end
   $scope module register_file $end
    $var wire  5 : AD1_i [4:0] $end
    $var wire  5 ; AD2_i [4:0] $end
    $var wire  5 < AD3_i [4:0] $end
    $var wire 32 e ADDRESS_WIDTH [31:0] $end
    $var wire 32 d DATA_WIDTH [31:0] $end
    $var wire 32 ) RD1_o [31:0] $end
    $var wire 32 * RD2_o [31:0] $end
    $var wire 32 = WD3_i [31:0] $end
    $var wire  1 3 WE3_i $end
    $var wire 32 c a0_o [31:0] $end
    $var wire  1 b clk $end
    $var wire 32 @ register_array[0] [31:0] $end
    $var wire 32 J register_array[10] [31:0] $end
    $var wire 32 K register_array[11] [31:0] $end
    $var wire 32 L register_array[12] [31:0] $end
    $var wire 32 M register_array[13] [31:0] $end
    $var wire 32 N register_array[14] [31:0] $end
    $var wire 32 O register_array[15] [31:0] $end
    $var wire 32 P register_array[16] [31:0] $end
    $var wire 32 Q register_array[17] [31:0] $end
    $var wire 32 R register_array[18] [31:0] $end
    $var wire 32 S register_array[19] [31:0] $end
    $var wire 32 A register_array[1] [31:0] $end
    $var wire 32 T register_array[20] [31:0] $end
    $var wire 32 U register_array[21] [31:0] $end
    $var wire 32 V register_array[22] [31:0] $end
    $var wire 32 W register_array[23] [31:0] $end
    $var wire 32 X register_array[24] [31:0] $end
    $var wire 32 Y register_array[25] [31:0] $end
    $var wire 32 Z register_array[26] [31:0] $end
    $var wire 32 [ register_array[27] [31:0] $end
    $var wire 32 \ register_array[28] [31:0] $end
    $var wire 32 ] register_array[29] [31:0] $end
    $var wire 32 B register_array[2] [31:0] $end
    $var wire 32 ^ register_array[30] [31:0] $end
    $var wire 32 _ register_array[31] [31:0] $end
    $var wire 32 C register_array[3] [31:0] $end
    $var wire 32 D register_array[4] [31:0] $end
    $var wire 32 E register_array[5] [31:0] $end
    $var wire 32 F register_array[6] [31:0] $end
    $var wire 32 G register_array[7] [31:0] $end
    $var wire 32 H register_array[8] [31:0] $end
    $var wire 32 I register_array[9] [31:0] $end
    $scope module unnamedblk1 $end
     $var wire 32 # i [31:0] $end
    $upscope $end
   $upscope $end
   $scope module rom $end
    $var wire 32 f DATA_W [31:0] $end
    $var wire 32 d WIDTH [31:0] $end
    $var wire 32 ' a_i [31:0] $end
    $var wire 32 . rd_o [31:0] $end
   $upscope $end
  $upscope $end
 $upscope $end
$enddefinitions $end


#0
b00000000000000000000000000000000 #
b00000000000000000000000000000100 $
b00000000000000000000000000000000 %
b00000000000000000000000000000100 &
b00000000000000000000000000000000 '
0(
b00000000000000000000000000000000 )
b00000000000000000000000000000000 *
b00000000000000000000000000000000 +
1,
b00000000000000000000000000000000 -
b00000000000000000000000000000000 .
b0000000 /
b000 0
01
02
03
b0000 4
05
b000 6
07
08
09
b00000 :
b00000 ;
b00000 <
b00000000000000000000000000000000 =
b00000000000000000000000000000000 >
b00000000000000000000000000000000 ?
b00000000000000000000000000000000 @
b00000000000000000000000000000000 A
b00000000000000000000000000000000 B
b00000000000000000000000000000000 C
b00000000000000000000000000000000 D
b00000000000000000000000000000000 E
b00000000000000000000000000000000 F
b00000000000000000000000000000000 G
b00000000000000000000000000000000 H
b00000000000000000000000000000000 I
b00000000000000000000000000000000 J
b00000000000000000000000000000000 K
b00000000000000000000000000000000 L
b00000000000000000000000000000000 M
b00000000000000000000000000000000 N
b00000000000000000000000000000000 O
b00000000000000000000000000000000 P
b00000000000000000000000000000000 Q
b00000000000000000000000000000000 R
b00000000000000000000000000000000 S
b00000000000000000000000000000000 T
b00000000000000000000000000000000 U
b00000000000000000000000000000000 V
b00000000000000000000000000000000 W
b00000000000000000000000000000000 X
b00000000000000000000000000000000 Y
b00000000000000000000000000000000 Z
b00000000000000000000000000000000 [
b00000000000000000000000000000000 \
b00000000000000000000000000000000 ]
b00000000000000000000000000000000 ^
b00000000000000000000000000000000 _
0`
0a
0b
b00000000000000000000000000000000 c
b00000000000000000000000000100000 d
b00000000000000000000000000000101 e
b00000000000000000000000000001000 f
#1
b00000000000000000000000000100000 #
b00000000000000000000000011111111 %
b00000000000000000000000011111111 +
0,
b00000000000000000000000011111111 -
b00001111111100000000001100010011 .
b0010011 /
13
15
b11111 ;
b00110 <
b00000000000000000000000011111111 =
b00000000000000000000000011111111 >
1b
#2
1`
0b
#3
b00000000000000000000000011111111 F
1b
#4
0b
#5
1b
#6
0`
0b
#7
b00000000000000000000000000001000 $
b00000000000000000000000000000100 %
b00000000000000000000000000001000 &
b00000000000000000000000000000100 '
b00000000000000000000000000000000 +
1,
b00000000000000000000000000000000 -
b00000000000000000000010100010011 .
b00000 ;
b01010 <
b00000000000000000000000000000000 =
b00000000000000000000000000000000 >
b11111111111111111111111111011101 ?
1b
#8
0b
#9
b00000000000000000000000000001100 $
b00000000000000000000000011111000 %
b00000000000000000000000000001100 &
b00000000000000000000000000001000 '
b00000000000000000000000011110000 +
0,
b00000000000000000000000011110000 -
b00001111000000000000010110010011 .
b10000 ;
b01011 <
b00000000000000000000000011110000 =
b00000000000000000000000011110000 >
b00000000000000000000000000000000 ?
1b
#10
0b
#11
b00000000000000000000000000010000 $
b00000000000000000000000000001100 %
b00000000000000000000000000010000 &
b00000000000000000000000000001100 '
b00000000000000000000000011110000 )
b00000000000000000000000000000000 +
b00000000000001011000010100010011 .
b01011 :
b00000 ;
b01010 <
b00000000000000000000000000000000 >
b00000000000000000000000011110000 K
1b
#12
0b
#13
b00000000000000000000000000010100 $
b00000000000000000000000000010001 %
b00000000000000000000000000010100 &
b00000000000000000000000000010000 '
b00000000000000000000000000000001 +
b00000000000000000000000011110001 -
b00000000000101011000010110010011 .
b00001 ;
b01011 <
b00000000000000000000000011110001 =
b00000000000000000000000000000001 >
b00000000000000000000000011110000 J
1b
b00000000000000000000000011110000 c
#14
0b
#15
b00000000000000000000000000011000 $
b11111111111111111111111111110110 %
b11111111111111111111111111110110 &
b00000000000000000000000000010100 '
1(
b00000000000000000000000011110001 )
b00000000000000000000000011111111 *
b00000000000000000000000011111111 +
1,
b00000000000000000000000111110000 -
b11111110011001011001100011100011 .
b1100011 /
b001 0
11
03
05
b010 6
17
b00110 ;
b10001 <
b00000000000000000000000111110000 =
b11111111111111111111111111100010 >
b00000000000000000000000011110001 K
1b
#16
0b
#17
b11111111111111111111111111111010 $
b11111111111111111111111111111010 &
b11111111111111111111111111110110 '
0(
b00000000000000000000000000000000 )
b00000000000000000000000000000000 *
b00000000000000000000000000000000 +
b00000000000000000000000000000000 -
b00000000000000000000000000000000 .
b0000000 /
b000 0
01
b000 6
07
b00000 :
b00000 ;
b00000 <
b00000000000000000000000000000000 =
b00000000000000000000000000000000 >
b11111111111111111111111111011101 ?
1b
#18
0b
#19
b11111111111111111111111111111110 $
b11111111111111111111111111111010 %
b11111111111111111111111111111110 &
b11111111111111111111111111111010 '
1b
#20
0b
#21
b00000000000000000000000000000010 $
b11111111111111111111111111111110 %
b00000000000000000000000000000010 &
b11111111111111111111111111111110 '
b00000000000000000000111111110000 .
b1110000 /
b11111 <
1b
#22
0b
#23
b00000000000000000000000000000110 $
b00000000000000000000000000110011 %
b00000000000000000000000000000110 &
b00000000000000000000000000000010 '
b00000000000000000000000011111111 )
0,
b00000000000000000000000011111111 -
b00000011000100110000000000000000 .
b0000000 /
b00110 :
b10001 ;
b00000 <
b00000000000000000000000011111111 =
b00000000000000000000000000110001 >
b00000000000000000000000000000000 ?
1b
#24
0b
#25
b00000000000000000000000000001010 $
b00000000000000000000000001010111 %
b00000000000000000000000000001010 &
b00000000000000000000000000000110 '
b00000101000100110000111100000000 .
b11110 <
b00000000000000000000000001010001 >
1b
#26
0b
#27
b00000000000000000000000000001110 $
b00000000000000000000000001100011 %
b00000000000000000000000000001110 &
b00000000000000000000000000001010 '
b00000101100100110000000000000101 .
b0000101 /
b11001 ;
b00000 <
b00000000000000000000000001011001 >
1b
#28
0b
#29
b00000000000000000000000000010010 $
b11111111111111111111100001011111 %
b00000000000000000000000000010010 &
b00000000000000000000000000001110 '
b10000101000100110000000000010101 .
b0010101 /
b10001 ;
b11111111111111111111100001010001 >
1b
#30
0b
#31
b00000000000000000000000000010110 $
b11111111111111111111100001101011 %
b00000000000000000000000000010110 &
b00000000000000000000000000010010 '
b00000000000000000000000000000000 )
b00000000000000000000000000000000 -
b10000101100100111111111001100101 .
b1100101 /
b111 0
b00111 :
b11001 ;
b11100 <
b00000000000000000000000000000000 =
b11111111111111111111100001011001 >
b11111111111111111111111111011101 ?
1b
#32
0b
#33
b00000000000000000000000000011010 $
b11111111111111111111100110100100 %
b00000000000000000000000000011010 &
b00000000000000000000000000010110 '
b11111111111111111111100110001110 +
b11111111111111111111100110001110 -
b10011000111000111111111000000011 .
b0000011 /
13
b1111 4
15
19
b01110 ;
b11111111111111111111100110001110 >
b00000000000000000000000000000000 ?
1b
#34
0b
#35
b00000000000000000000000000011110 $
b00000000000000000000000100011010 %
b00000000000000000000000000011110 &
b00000000000000000000000000011010 '
b00000000000000000000000000000000 +
1,
b00000000000000000000000000000000 -
b00010000000000000000000000000000 .
b0000000 /
b000 0
03
05
09
b00000 :
b00000 ;
b00000 <
b00000000000000000000000100000000 >
b11111111111111111111111111011101 ?
1b
#36
0b
#37
b00000000000000000000000000100010 $
b00000000000000000000000000011110 %
b00000000000000000000000000100010 &
b00000000000000000000000000011110 '
b00000000000000000000000000000000 .
b00000000000000000000000000000000 >
1b
#38
0b
#39
b00000000000000000000000000100110 $
b00000000000000000000000000100010 %
b00000000000000000000000000100110 &
b00000000000000000000000000100010 '
1b
#40
0b
#41
b00000000000000000000000000101010 $
b00000000000000000000000000100110 %
b00000000000000000000000000101010 &
b00000000000000000000000000100110 '
1b
#42
0b
#43
b00000000000000000000000000101110 $
b00000000000000000000000000101010 %
b00000000000000000000000000101110 &
b00000000000000000000000000101010 '
1b
#44
0b
#45
b00000000000000000000000000110010 $
b00000000000000000000000000101110 %
b00000000000000000000000000110010 &
b00000000000000000000000000101110 '
1b
#46
0b
#47
b00000000000000000000000000110110 $
b00000000000000000000000000110010 %
b00000000000000000000000000110110 &
b00000000000000000000000000110010 '
1b
#48
0b
#49
b00000000000000000000000000111010 $
b00000000000000000000000000110110 %
b00000000000000000000000000111010 &
b00000000000000000000000000110110 '
1b
#50
0b
#51
b00000000000000000000000000111110 $
b00000000000000000000000000111010 %
b00000000000000000000000000111110 &
b00000000000000000000000000111010 '
1b
#52
0b
#53
b00000000000000000000000001000010 $
b00000000000000000000000000111110 %
b00000000000000000000000001000010 &
b00000000000000000000000000111110 '
1b
#54
0b
#55
b00000000000000000000000001000110 $
b00000000000000000000000001000010 %
b00000000000000000000000001000110 &
b00000000000000000000000001000010 '
1b
#56
0b
#57
b00000000000000000000000001001010 $
b00000000000000000000000001000110 %
b00000000000000000000000001001010 &
b00000000000000000000000001000110 '
1b
#58
0b
#59
b00000000000000000000000001001110 $
b00000000000000000000000001001010 %
b00000000000000000000000001001110 &
b00000000000000000000000001001010 '
1b
#60
0b
#61
b00000000000000000000000001010010 $
b00000000000000000000000001001110 %
b00000000000000000000000001010010 &
b00000000000000000000000001001110 '
1b
#62
0b
#63
b00000000000000000000000001010110 $
b00000000000000000000000001010010 %
b00000000000000000000000001010110 &
b00000000000000000000000001010010 '
1b
#64
0b
#65
b00000000000000000000000001011010 $
b00000000000000000000000001010110 %
b00000000000000000000000001011010 &
b00000000000000000000000001010110 '
1b
#66
0b
#67
b00000000000000000000000001011110 $
b00000000000000000000000001011010 %
b00000000000000000000000001011110 &
b00000000000000000000000001011010 '
1b
#68
0b
#69
b00000000000000000000000001100010 $
b00000000000000000000000001011110 %
b00000000000000000000000001100010 &
b00000000000000000000000001011110 '
1b
#70
0b
#71
b00000000000000000000000001100110 $
b00000000000000000000000001100010 %
b00000000000000000000000001100110 &
b00000000000000000000000001100010 '
1b
#72
0b
#73
b00000000000000000000000001101010 $
b00000000000000000000000001100110 %
b00000000000000000000000001101010 &
b00000000000000000000000001100110 '
1b
#74
0b
#75
b00000000000000000000000001101110 $
b00000000000000000000000001101010 %
b00000000000000000000000001101110 &
b00000000000000000000000001101010 '
1b
#76
0b
#77
b00000000000000000000000001110010 $
b00000000000000000000000001101110 %
b00000000000000000000000001110010 &
b00000000000000000000000001101110 '
1b
#78
0b
#79
b00000000000000000000000001110110 $
b00000000000000000000000001110010 %
b00000000000000000000000001110110 &
b00000000000000000000000001110010 '
1b
#80
0b
#81
b00000000000000000000000001111010 $
b00000000000000000000000001110110 %
b00000000000000000000000001111010 &
b00000000000000000000000001110110 '
1b
#82
0b
#83
b00000000000000000000000001111110 $
b00000000000000000000000001111010 %
b00000000000000000000000001111110 &
b00000000000000000000000001111010 '
1b
#84
0b
